stereodemo/__init__.py
stereodemo/__main__.py
stereodemo/chang_realtime_stereo_onnx.py
stereodemo/main.py
stereodemo/method_chang_realtime_stereo.py
stereodemo/method_cre_stereo.py
stereodemo/method_dist_depth.py
stereodemo/method_hitnet.py
stereodemo/method_opencv_bm.py
stereodemo/method_raft_stereo.py
stereodemo/method_sttr.py
stereodemo/methods.py
stereodemo/oakd_source.py
stereodemo/utils.py
stereodemo/visualizer.py
stereodemo/datasets/oak-d/bedroom_chair_left.png
stereodemo/datasets/oak-d/bedroom_chair_right.png
stereodemo/datasets/oak-d/corridor_left.png
stereodemo/datasets/oak-d/corridor_right.png
stereodemo/datasets/oak-d/cycles_left.png
stereodemo/datasets/oak-d/cycles_right.png
stereodemo/datasets/oak-d/desk_left.png
stereodemo/datasets/oak-d/desk_right.png
stereodemo/datasets/oak-d/donkey_toy_left.png
stereodemo/datasets/oak-d/donkey_toy_right.png
stereodemo/datasets/oak-d/kid_bedroom_left.png
stereodemo/datasets/oak-d/kid_bedroom_right.png
stereodemo/datasets/oak-d/living_room_left.png
stereodemo/datasets/oak-d/living_room_right.png
stereodemo/datasets/oak-d/pov_controllers_left.png
stereodemo/datasets/oak-d/pov_controllers_right.png
stereodemo/datasets/oak-d/pov_hands_left.png
stereodemo/datasets/oak-d/pov_hands_right.png
stereodemo/datasets/oak-d/selfie_left.png
stereodemo/datasets/oak-d/selfie_right.png
stereodemo/datasets/oak-d/stairs_left.png
stereodemo/datasets/oak-d/stairs_right.png
stereodemo/datasets/oak-d/stereodemo_calibration.json
stereodemo/datasets/oak-d/toy_left.png
stereodemo/datasets/oak-d/toy_right.png
stereodemo-0.6.2.dist-info/licenses/LICENSE
stereodemo-0.6.2.dist-info/METADATA
stereodemo-0.6.2.dist-info/WHEEL
stereodemo-0.6.2.dist-info/entry_points.txt
stereodemo-0.6.2.dist-info/top_level.txt
stereodemo-0.6.2.dist-info/RECORD
