Metadata-Version: 2.4
Name: stereodemo
Version: 0.6.2
Summary: Compare various stereo depth estimation algorithms on image files or with an OAK-D camera.
Home-page: https://github.com/nburrus/stereodemo
Author: Nicolas Burrus
Author-email: nicolas@burrus.name
Project-URL: Bug Tracker, https://github.com/nburrus/stereodemo/issues
Classifier: Programming Language :: Python :: 3
Classifier: License :: OSI Approved :: MIT License
Classifier: Operating System :: OS Independent
Requires-Python: >=3.8
License-File: LICENSE
Requires-Dist: numpy
Requires-Dist: onnxruntime>=1.10.0; sys_platform == "darwin"
Requires-Dist: onnxruntime-gpu>=1.10.0; sys_platform != "darwin"
Requires-Dist: opencv-python
Requires-Dist: open3d>=0.15.1
Requires-Dist: torch>=1.11.0
Requires-Dist: torchvision
Dynamic: license-file
